Metadata-Version: 2.1
Name: gentk
Version: 1.0.0
Summary: 4D Genome Toolkit.
Home-page: https://github.com/lanl/4DGB
Author: David H. Rogers
Author-email: dhr@lanl.gov
License: UNKNOWN
Platform: UNKNOWN
Classifier: Programming Language :: Python :: 3
Classifier: License :: OSI Approved :: BSD License
Classifier: Operating System :: OS Independent
